{
  "data": {
    "id": 77587,
    "host_id": 24625,
    "name": "C\u0102N H\u1ed8 1 PH\u00d2NG NG\u1ee6 - R\u1ed0N STUDIO",
    "summary": "",
    "introduction": "<ul><li><p>C\u0103n h\u1ed9 1 ph\u00f2ng + 1 wc v\u1edbi di\u1ec7n t\u00edch 30m2 th\u00edch h\u1ee3p cho 2 - 4 kh\u00e1ch<\/p><\/li><li><p>G\u1ea7n nhi\u1ec1u \u0111\u1ecba \u0111i\u1ec3m du l\u1ecbch n\u1ed5i ti\u1ebfng: nh\u00e0 th\u1edd con G\u00e0, h\u1ed3 Tuy\u1ec1n L\u00e2m, c\u00e1p treo, v\u01b0\u1eddn hoa \u0110\u00e0 L\u1ea1t, si\u00eau th\u1ecb Big C, H\u1ed3 Xu\u00e2n H\u01b0\u01a1ng, thi\u1ec1n vi\u1ec7n Tr\u00fac L\u00e2m, ch\u00f9a Linh Ph\u01b0\u1edbc, Crazy house,\u2026<\/p><\/li><li><p>G\u1ea7n c\u00e1c qu\u00e1n \u0103n, coffee n\u1ed5i ti\u1ebfng: down under, anna\u2019s coffee house,\u2026<\/p><\/li><li><p>C\u00e1ch Dinh B\u1ea3o \u0110\u1ea1i: 3km<\/p><\/li><li><p>Qu\u1ea3ng tr\u01b0\u1eddng L\u00e2m Vi\u00ean: 7km<\/p><\/li><li><p>C\u00e1ch trung t\u00e2m: 2km<\/p><\/li><\/ul><ul><li><p>C\u0103n h\u1ed9 g\u1ed3m c\u00f3 09 studio, b\u1ebfp ri\u00eang<\/p><\/li><li><p>C\u00f3 khu\u00f4n vi\u00ean chung<\/p><\/li><li><p>S\u00e2n chung cho kh\u00e1ch BBQ, \u0111\u1ed1t l\u1eeda tr\u1ea1i r\u1ed9ng r\u00e3i, tho\u1ea3i m\u00e1i<\/p><\/li><li><p>C\u00f3 gara \u0111\u1eadu xe, h\u1ebbm xe 16c ra v\u00e0o tho\u1ea3i m\u00e1i<\/p><\/li><li><p>Giao ch\u00eca kh\u00f3a nguy\u00ean c\u0103n<\/p><p><strong>D\u1ecbch v\u1ee5 mi\u1ec5n ph\u00ed:<\/strong><\/p><ul><li><p>Gia v\u1ecb c\u01a1 b\u1ea3n<\/p><\/li><li><p>Tr\u00e0, cafe, n\u01b0\u1edbc su\u1ed1i<\/p><\/li><li><p>B\u1ebfp \u0111\u1ea7y \u0111\u1ee7 d\u1ee5ng c\u1ee5 n\u1ea5u \u0103n<\/p><\/li><li><p>Nh\u00e2n vi\u00ean ch\u0103m s\u00f3c kh\u00e1ch<\/p><\/li><li><p>\u0110\u1ed3 d\u00f9ng v\u1ec7 sinh c\u00e1 nh\u00e2n ( d\u1ea7u g\u1ed9i, s\u1eefa t\u1eafm, b\u00e0n ch\u1ea3i, d\u00e9p \u0111i trong nh\u00e0,&nbsp;<strong>)<\/strong><\/p><\/li><li><p>B\u00e3i \u0111\u1eadu xe \u00f4 t\u00f4 an to\u00e0n t\u1eeb 4 -45 ch\u1ed7<\/p><\/li><\/ul><\/li><\/ul>",
    "introduction_ko": "",
    "unique_features": null,
    "utilities": null,
    "host_experiences": null,
    "special_note": "<p>\u00a7&nbsp; Gi\u1edd check in: 14h \u2013 check out: 12h (n\u1ebfu kh\u00e1ch h\u00e0ng c\u00f3 nhu c\u1ea7u c\u1ea7n check in- check out kh\u00e1c gi\u1edd quy \u0111\u1ecbnh li\u00ean h\u1ec7 nh\u00e2n vi\u00ean kinh doanh)<\/p><p>\u00a7&nbsp; Gi\u00e1 tr\u00ean \u00e1p d\u1ee5ng theo s\u1ed1 l\u01b0\u1ee3ng ph\u00f2ng. Kh\u00e1ch ph\u00e1t sinh ph\u1ee5 thu theo quy \u0111\u1ecbnh (150.000 vnd\/pax)<\/p><p>\u00a7&nbsp; Tr\u1ebb em d\u01b0\u1edbi 6+ mi\u1ec5n ph\u00ed v\u00ec ng\u1ee7 chung v\u1edbi b\u1ed1 m\u1eb9.<\/p><p>\u00a7&nbsp; Tr\u1ebb em tr\u00ean 6+ ph\u1ee5 thu nh\u01b0 ng\u01b0\u1eddi l\u1edbn .<\/p><p>\u00a7&nbsp; C\u0103n h\u1ed9 kh\u00f4ng bao g\u1ed3m gia v\u1ecb, qu\u00fd kh\u00e1ch t\u1ef1 chu\u1ea9n b\u1ecb<\/p><p>\u00a7&nbsp; C\u0103n h\u1ed9 theo h\u00ecnh th\u1ee9c giao nguy\u00ean c\u0103n, kh\u00f4ng bao g\u1ed3m ph\u00ed d\u1ecdn v\u1ec7 sinh h\u1eb1ng ng\u00e0y. Q\u00fay kh\u00e1ch c\u00f3 nhu c\u1ea7u d\u1ecdn ph\u00f2ng vui l\u00f2ng li\u00ean h\u1ec7 nh\u00e2n vi\u00ean<\/p><p>\u00a7&nbsp; C\u0103n h\u1ed9 kh\u00f4ng c\u00f3 ph\u00f2ng n\u1ed9i b\u1ed9 cho t\u00e0i x\u1ebf<\/p><p>\u00a7&nbsp; Sau khi s\u1eed d\u1ee5ng b\u1ebfp, qu\u00fd kh\u00e1ch vui l\u00f2ng t\u1ef1 d\u1ecdn r\u1eeda. Qu\u00fd kh\u00e1ch c\u00f3 nhu c\u1ea7u thu\u00ea nh\u00e2n vi\u00ean d\u1ecdn r\u1eeda vui l\u00f2ng li\u00ean h\u1ec7 qu\u1ea3n gia.<\/p><p>\u00a7&nbsp; Kh\u00f4ng h\u00e1t karaoke, l\u00e0m \u1ed3n sau 21h theo quy \u0111\u1ecbnh nh\u00e0 n\u01b0\u1edbc.<\/p><p>\u00a7&nbsp; Vui l\u00f2ng xu\u1ea5t tr\u00ecnh h\u1ed9 chi\u1ebfu c\u00f3 th\u1ecb th\u1ef1c xu\u1ea5t nh\u1eadp c\u1ea3nh h\u1ee3p l\u1ec7 khi l\u00e0m th\u1ee7 t\u1ee5c nh\u1eadn ph\u00f2ng (CMND n\u1ebfu l\u00e0 c\u00f4ng d\u00e2n qu\u1ed1c t\u1ecbch Vi\u1ec7t Nam).<\/p><p>\u00a7&nbsp; Nghi\u00eam c\u1ea5m vi\u1ec7c mang v\u00e0o c\u0103n h\u1ed9 nh\u01b0 v\u0169 kh\u00ed, \u0111\u1ed9c d\u01b0\u1ee3c , ma t\u00fay ,c\u00e1c ch\u1ea5t c\u1ea5m v\u00e0 c\u00e1c ch\u1ea5t g\u00e2y n\u1ed5 kh\u00e1c.<\/p><p>\u00a7&nbsp; Nghi\u00eam c\u1ea5m m\u1ecdi h\u00ecnh th\u1ee9c c\u1edd b\u1ea1c, s\u1eed d\u1ee5ng ma t\u00fay trong khu v\u1ef1c c\u0103n h\u1ed9. Qu\u00fd kh\u00e1ch ph\u1ea3i ho\u00e0n to\u00e0n ch\u1ecbu tr\u00e1ch nhi\u1ec7m tr\u01b0\u1edbc ph\u00e1p lu\u1eadt Vi\u1ec7t Nam v\u00e0 c\u0103n h\u1ed9 n\u1ebfu vi ph\u1ea1m.<\/p><p>\u00a7&nbsp; Ng\u01b0\u1eddi th\u00e2n \u0111\u1ebfn th\u0103m ph\u1ea3i \u0111\u0103ng k\u00ed v\u1edbi qu\u1ea3n gia. Ng\u01b0\u1eddi th\u00e2n ch\u1ec9 c\u00f3 th\u1ec3 \u0111\u01b0\u1ee3c \u0111\u0103ng k\u00fd t\u1eeb 09h00 \u0111\u1ebfn 21h00.<\/p>",
    "apartment_rules": "Y\u00eau c\u1ea7u ch\u1ee9ng minh th\u01b0\/ c\u0103n c\u01b0\u1edbc c\u00f4ng d\u00e2n\/ h\u1ed9 chi\u1ebfu ho\u1eb7c \u0111\u1eb7t c\u1ecdc t\u1ea1i ch\u1ed7 ngh\u1ec9\\nH\u1ea1n ch\u1ebf l\u00e0m \u1ed3n sau 10 gi\u1edd t\u1ed1i\\nKh\u00f4ng \u0111i gi\u00e0y\/d\u00e9p trong nh\u00e0\\n",
    "apartment_manual": "<p>\u00a7&nbsp; Gi\u1edd check in: 14h \u2013 check out: 12h (n\u1ebfu kh\u00e1ch h\u00e0ng c\u00f3 nhu c\u1ea7u c\u1ea7n check in_check out kh\u00e1c gi\u1edd quy \u0111\u1ecbnh li\u00ean h\u1ec7 nh\u00e2n vi\u00ean kinh doanh)<\/p>\\n<p>Tr\u01b0\u1edbc ng\u00e0y check in nh\u00e2n vi\u00ean s\u1ebd ch\u1ee7 \u0111\u1ed9ng li\u00ean h\u1ec7 v\u00e0 b\u00e0n giao c\u0103n h\u1ed9 cho kh\u00e1ch<\/p><p>N\u1ebfu kh\u00f4ng th\u1ec3 ch\u1edd \u0111\u1ee3i \u0111\u01b0\u1ee3c vui l\u00f2ng li\u00ean h\u1ec7 s\u1ed1 hot line: 0907813722<\/p>\\n",
    "direction_manual": null,
    "checkin_guide": null,
    "num_bedrooms": 1,
    "num_bathrooms": 1,
    "num_beds": 1,
    "area": "30",
    "maximum_guests": 4,
    "booking_type": "instant_book",
    "calendar_type": null,
    "status": "Listed",
    "submit_status": "Reject",
    "cancellation_policy": "Moderate",
    "url": "https:\/\/www.luxstay.com\/rooms\/77587",
    "rating": 0,
    "review_count": 0,
    "like_count": 37,
    "favourable_rates": 100,
    "max_infants": null,
    "instant_fake": false,
    "partner_room": false,
    "featured_photo": "https:\/\/cdn.luxstay.com\/users\/13315\/5hwqxu3ptcAR3a04SgnS41Qm.jpg",
    "bedType": {
      "data": {
        "id": 4,
        "name": "Couch"
      }
    },
    "roomType": {
      "data": {
        "id": 2,
        "name": "Ph\u00f2ng ri\u00eang",
        "description": "Ph\u00f2ng ri\u00eang"
      }
    },
    "propertyType": {
      "data": {
        "id": 28,
        "name": "C\u0103n h\u1ed9 Studio",
        "description": "C\u0103n h\u1ed9 lo\u1ea1i nh\u1ecf, kh\u00f4ng ph\u00e2n chia kh\u00f4ng gian, v\u1edbi di\u1ec7n t\u00edch t\u1ed1i \u0111a ch\u1ec9 kho\u1ea3ng 60 m2"
      }
    },
    "price": {
      "data": {
        "room_id": 77587,
        "nightly_price": 600000,
        "monthly_price": 576000,
        "weekend_price": 700000,
        "cleaning_fee": 100000,
        "security_fee": 0,
        "nightly_price_formatted": "600,000\u20ab",
        "cleaning_fee_formatted": "100,000\u20ab",
        "security_fee_formatted": "0\u20ab",
        "additional_guests_fee": 100000,
        "additional_children_fee": 100000,
        "additional_infants_fee": 0,
        "currency_code": "VND",
        "standard_guests": 2,
        "standard_children": 2,
        "standard_infants": 1,
        "cancellation_policy": "Moderate",
        "booking_type": "instant_book",
        "checkin_time": "02:00 pm",
        "checkout_time": "12:00 pm",
        "checkin_time_expiry": null,
        "minimum_stay": 1,
        "maximum_stay": 90,
        "nightly_price_usd": 25.440469936360664,
        "nightly_price_vnd": 600000
      }
    },
    "address": {
      "data": {
        "address_line_1": "H\u1ebaM 36 TRI\u1ec6U VI\u1ec6T V\u01af\u01a0NG,  TRI\u1ec6U VI\u1ec6T V\u01af\u01a0NG,  Ph\u01b0\u1eddng 3,  Th\u00e0nh ph\u1ed1 \u0110\u00e0 L\u1ea1t,  T\u1ec9nh L\u00e2m \u0110\u1ed3ng,  Viet Nam",
        "address_line_2": null,
        "area": "2773",
        "area_id": 2773,
        "area_path": "vietnam\/lam-dong\/da-lat\/2773",
        "city": "\u0110\u00e0 L\u1ea1t",
        "city_id": 2767,
        "city_path": "vietnam\/lam-dong\/da-lat",
        "state": "L\u00e2m \u0110\u1ed3ng",
        "state_id": 2716,
        "state_path": "vietnam\/lam-dong",
        "country": "Vietnam",
        "country_path": "vietnam",
        "latitude": "11.9302439",
        "longitude": "108.4319915",
        "full_address": "H\u1ebaM 36 TRI\u1ec6U VI\u1ec6T V\u01af\u01a0NG,  TRI\u1ec6U VI\u1ec6T V\u01af\u01a0NG,  Ph\u01b0\u1eddng 3,  Th\u00e0nh ph\u1ed1 \u0110\u00e0 L\u1ea1t,  T\u1ec9nh L\u00e2m \u0110\u1ed3ng,  Viet Nam"
      }
    },
    "host": {
      "data": {
        "id": 24625,
        "full_name": "Qu\u00e1cht\u01b0\u1eddng Vi",
        "created_at": "2018-10-24T11:12:06+00:00",
        "avatar": "https:\/\/cdn.luxstay.com\/users\/24625\/1541109350_img_2370jpg",
        "tiny_avatar": "https:\/\/cdn.luxstay.com\/users\/24625\/1541109350_img_2370jpg",
        "about": "Hy v\u1ecdng mang \u0111\u1ebfn cho du kh\u00e1ch \u0111\u1ebfn \u0110\u00e0 L\u1ea1t 1 ch\u1ed7 l\u01b0u tr\u00fa ti\u1ec7n nghi, \u0111\u1eb3ng c\u1ea5p , th\u00e2n thi\u00ean, tho\u1ea3i m\u00e1i. Quan tr\u1ecdng h\u01a1n h\u1ebft l\u00e0 gi\u00e1 ph\u1ea3i r\u1ebb",
        "email": "beuthouse@gmail.com",
        "email_verified": false,
        "phone_verified": false,
        "subscribe_url": "\/api\/me\/subscriptions\/user\/24625",
        "super_host": false,
        "phone": "0907813722",
        "response_rate": 100,
        "cancellation_rate": 0,
        "rooms": 21,
        "cc_mails": null
      }
    },
    "photos": {
      "data": [
        {
          "id": 4561822,
          "slide": true,
          "photo_url": "https:\/\/cdn.luxstay.com\/users\/13315\/5hwqxu3ptcAR3a04SgnS41Qm.jpg",
          "thumbnail": "https:\/\/cdn.luxstay.com\/users\/13315\/5hwqxu3ptcAR3a04SgnS41Qm.jpg"
        },
        {
          "id": 4561821,
          "slide": true,
          "photo_url": "https:\/\/cdn.luxstay.com\/users\/13315\/RuMUrHbLIhmL3yPd4G7esKeQ.jpeg",
          "thumbnail": "https:\/\/cdn.luxstay.com\/users\/13315\/RuMUrHbLIhmL3yPd4G7esKeQ.jpeg"
        },
        {
          "id": 4561820,
          "slide": true,
          "photo_url": "https:\/\/cdn.luxstay.com\/users\/13315\/EuQYIpzQKdfX1Hxl8gr-MNaL.jpeg",
          "thumbnail": "https:\/\/cdn.luxstay.com\/users\/13315\/EuQYIpzQKdfX1Hxl8gr-MNaL.jpeg"
        },
        {
          "id": 4561819,
          "slide": true,
          "photo_url": "https:\/\/cdn.luxstay.com\/users\/13315\/oZrdWX6sgfr1wf_NeDYFLxEC.jpg",
          "thumbnail": "https:\/\/cdn.luxstay.com\/users\/13315\/oZrdWX6sgfr1wf_NeDYFLxEC.jpg"
        },
        {
          "id": 4561818,
          "slide": true,
          "photo_url": "https:\/\/cdn.luxstay.com\/users\/13315\/LI6Ocg2_U-eG3GAs2NxOYl1T.jpg",
          "thumbnail": "https:\/\/cdn.luxstay.com\/users\/13315\/LI6Ocg2_U-eG3GAs2NxOYl1T.jpg"
        },
        {
          "id": 4561817,
          "slide": true,
          "photo_url": "https:\/\/cdn.luxstay.com\/users\/13315\/VbYLt92MqQmxjJNij0T1KCis.jpg",
          "thumbnail": "https:\/\/cdn.luxstay.com\/users\/13315\/VbYLt92MqQmxjJNij0T1KCis.jpg"
        },
        {
          "id": 4561816,
          "slide": true,
          "photo_url": "https:\/\/cdn.luxstay.com\/users\/13315\/cTtTMbAsCQ3A5wOb2BnAji8P.jpg",
          "thumbnail": "https:\/\/cdn.luxstay.com\/users\/13315\/cTtTMbAsCQ3A5wOb2BnAji8P.jpg"
        },
        {
          "id": 4561815,
          "slide": true,
          "photo_url": "https:\/\/cdn.luxstay.com\/users\/13315\/KpK-pnRPt5emBFReuk1AHjrx.jpg",
          "thumbnail": "https:\/\/cdn.luxstay.com\/users\/13315\/KpK-pnRPt5emBFReuk1AHjrx.jpg"
        },
        {
          "id": 4561814,
          "slide": true,
          "photo_url": "https:\/\/cdn.luxstay.com\/users\/13315\/RPLeP7KJkG8t6kc9nwZNkVDG.jpg",
          "thumbnail": "https:\/\/cdn.luxstay.com\/users\/13315\/RPLeP7KJkG8t6kc9nwZNkVDG.jpg"
        },
        {
          "id": 4561813,
          "slide": true,
          "photo_url": "https:\/\/cdn.luxstay.com\/users\/13315\/DO3a-hHUzD9KJdlGXOGCi7K5.jpg",
          "thumbnail": "https:\/\/cdn.luxstay.com\/users\/13315\/DO3a-hHUzD9KJdlGXOGCi7K5.jpg"
        }
      ]
    },
    "photoTags": {
      "data": [
        {
          "id": 0,
          "name": "Kh\u00e1c",
          "normalized": "other",
          "photos": {
            "data": [
              {
                "id": 4561822,
                "slide": true,
                "photo_url": "https:\/\/cdn.luxstay.com\/users\/13315\/5hwqxu3ptcAR3a04SgnS41Qm.jpg",
                "thumbnail": "https:\/\/cdn.luxstay.com\/users\/13315\/5hwqxu3ptcAR3a04SgnS41Qm.jpg"
              },
              {
                "id": 4561821,
                "slide": true,
                "photo_url": "https:\/\/cdn.luxstay.com\/users\/13315\/RuMUrHbLIhmL3yPd4G7esKeQ.jpeg",
                "thumbnail": "https:\/\/cdn.luxstay.com\/users\/13315\/RuMUrHbLIhmL3yPd4G7esKeQ.jpeg"
              },
              {
                "id": 4561820,
                "slide": true,
                "photo_url": "https:\/\/cdn.luxstay.com\/users\/13315\/EuQYIpzQKdfX1Hxl8gr-MNaL.jpeg",
                "thumbnail": "https:\/\/cdn.luxstay.com\/users\/13315\/EuQYIpzQKdfX1Hxl8gr-MNaL.jpeg"
              },
              {
                "id": 4561819,
                "slide": true,
                "photo_url": "https:\/\/cdn.luxstay.com\/users\/13315\/oZrdWX6sgfr1wf_NeDYFLxEC.jpg",
                "thumbnail": "https:\/\/cdn.luxstay.com\/users\/13315\/oZrdWX6sgfr1wf_NeDYFLxEC.jpg"
              },
              {
                "id": 4561818,
                "slide": true,
                "photo_url": "https:\/\/cdn.luxstay.com\/users\/13315\/LI6Ocg2_U-eG3GAs2NxOYl1T.jpg",
                "thumbnail": "https:\/\/cdn.luxstay.com\/users\/13315\/LI6Ocg2_U-eG3GAs2NxOYl1T.jpg"
              },
              {
                "id": 4561817,
                "slide": true,
                "photo_url": "https:\/\/cdn.luxstay.com\/users\/13315\/VbYLt92MqQmxjJNij0T1KCis.jpg",
                "thumbnail": "https:\/\/cdn.luxstay.com\/users\/13315\/VbYLt92MqQmxjJNij0T1KCis.jpg"
              },
              {
                "id": 4561816,
                "slide": true,
                "photo_url": "https:\/\/cdn.luxstay.com\/users\/13315\/cTtTMbAsCQ3A5wOb2BnAji8P.jpg",
                "thumbnail": "https:\/\/cdn.luxstay.com\/users\/13315\/cTtTMbAsCQ3A5wOb2BnAji8P.jpg"
              },
              {
                "id": 4561815,
                "slide": true,
                "photo_url": "https:\/\/cdn.luxstay.com\/users\/13315\/KpK-pnRPt5emBFReuk1AHjrx.jpg",
                "thumbnail": "https:\/\/cdn.luxstay.com\/users\/13315\/KpK-pnRPt5emBFReuk1AHjrx.jpg"
              },
              {
                "id": 4561814,
                "slide": true,
                "photo_url": "https:\/\/cdn.luxstay.com\/users\/13315\/RPLeP7KJkG8t6kc9nwZNkVDG.jpg",
                "thumbnail": "https:\/\/cdn.luxstay.com\/users\/13315\/RPLeP7KJkG8t6kc9nwZNkVDG.jpg"
              },
              {
                "id": 4561813,
                "slide": true,
                "photo_url": "https:\/\/cdn.luxstay.com\/users\/13315\/DO3a-hHUzD9KJdlGXOGCi7K5.jpg",
                "thumbnail": "https:\/\/cdn.luxstay.com\/users\/13315\/DO3a-hHUzD9KJdlGXOGCi7K5.jpg"
              }
            ]
          }
        }
      ]
    },
    "amenities": {
      "data": [
        {
          "id": 5,
          "name": "BBQ",
          "description": "",
          "icon": "lst-icon-bbq-facilities",
          "type": {
            "data": {
              "id": 3,
              "name": "Ti\u1ec7n \u00edch gi\u1ea3i tr\u00ed",
              "description": ""
            }
          }
        },
        {
          "id": 6,
          "name": "B\u1ebfp \u0111i\u1ec7n",
          "description": "",
          "icon": "lst-icon-stove-electric",
          "type": {
            "data": {
              "id": 2,
              "name": "Ti\u1ec7n \u00edch b\u1ebfp",
              "description": ""
            }
          }
        },
        {
          "id": 7,
          "name": "L\u00f2 vi s\u00f3ng",
          "description": "",
          "icon": "lst-icon-microwave",
          "type": {
            "data": {
              "id": 2,
              "name": "Ti\u1ec7n \u00edch b\u1ebfp",
              "description": ""
            }
          }
        },
        {
          "id": 8,
          "name": "T\u1ee7 l\u1ea1nh",
          "description": "",
          "icon": "lst-icon-refrigerator",
          "type": {
            "data": {
              "id": 2,
              "name": "Ti\u1ec7n \u00edch b\u1ebfp",
              "description": ""
            }
          }
        },
        {
          "id": 17,
          "name": "Wifi",
          "description": "",
          "icon": "lst-icon-hotel-wifi",
          "type": {
            "data": {
              "id": 6,
              "name": "Ti\u1ec7n \u00edch ",
              "description": ""
            }
          }
        },
        {
          "id": 22,
          "name": "Ban C\u00f4ng",
          "description": "",
          "icon": "lst-icon-balcony-terrace",
          "type": {
            "data": {
              "id": 5,
              "name": "Ti\u1ec7n \u00edch ph\u00f2ng",
              "description": ""
            }
          }
        },
        {
          "id": 27,
          "name": "TV",
          "description": "",
          "icon": "lst-icon-tv",
          "type": {
            "data": {
              "id": 6,
              "name": "Ti\u1ec7n \u00edch ",
              "description": ""
            }
          }
        },
        {
          "id": 36,
          "name": "Ph\u00f9 h\u1ee3p v\u1edbi tr\u1ebb nh\u1ecf",
          "description": "",
          "icon": "lst-icon-family-room",
          "type": {
            "data": {
              "id": 1,
              "name": "Ti\u1ec7n \u00edch gia \u0111\u00ecnh",
              "description": ""
            }
          }
        },
        {
          "id": 38,
          "name": "M\u00e1y gi\u1eb7t",
          "description": "",
          "icon": "lst-icon-washer",
          "type": {
            "data": {
              "id": 6,
              "name": "Ti\u1ec7n \u00edch ",
              "description": ""
            }
          }
        },
        {
          "id": 39,
          "name": "\u0110\u1ec7m b\u1ed5 sung",
          "description": "",
          "icon": "lst-icon-room-promotion",
          "type": {
            "data": {
              "id": 1,
              "name": "Ti\u1ec7n \u00edch gia \u0111\u00ecnh",
              "description": ""
            }
          }
        },
        {
          "id": 42,
          "name": "D\u1ea7u g\u1ed9i, d\u1ea7u x\u1ea3",
          "description": "",
          "icon": "lst-icon-shampoo",
          "type": {
            "data": {
              "id": 6,
              "name": "Ti\u1ec7n \u00edch ",
              "description": ""
            }
          }
        },
        {
          "id": 44,
          "name": "Gi\u1ea5y v\u1ec7 sinh",
          "description": "",
          "icon": "lst-icon-toilet-paper-1",
          "type": {
            "data": {
              "id": 6,
              "name": "Ti\u1ec7n \u00edch ",
              "description": ""
            }
          }
        },
        {
          "id": 53,
          "name": "Kh\u0103n t\u1eafm",
          "description": "",
          "icon": "lst-icon-towels",
          "type": {
            "data": {
              "id": 6,
              "name": "Ti\u1ec7n \u00edch ",
              "description": ""
            }
          }
        },
        {
          "id": 55,
          "name": "Kem \u0111\u00e1nh r\u0103ng",
          "description": "",
          "icon": "lst-icon-uniF12D",
          "type": {
            "data": {
              "id": 6,
              "name": "Ti\u1ec7n \u00edch ",
              "description": ""
            }
          }
        },
        {
          "id": 59,
          "name": "X\u00e0 ph\u00f2ng t\u1eafm",
          "description": "",
          "icon": "lst-icon-uniF126",
          "type": {
            "data": {
              "id": 6,
              "name": "Ti\u1ec7n \u00edch ",
              "description": ""
            }
          }
        },
        {
          "id": 66,
          "name": "Smart tivi",
          "description": "",
          "icon": "lst-icon-smart-tv",
          "type": {
            "data": {
              "id": 7,
              "name": "Ti\u1ec7n \u00edch n\u1ed5i b\u1eadt",
              "description": "Ti\u1ec7n \u00edch n\u1ed5i b\u1eadt"
            }
          }
        },
        {
          "id": 69,
          "name": "M\u00e1y s\u1ea5y",
          "description": "",
          "icon": "lst-icon-hair-dryer",
          "type": {
            "data": {
              "id": 6,
              "name": "Ti\u1ec7n \u00edch ",
              "description": ""
            }
          }
        },
        {
          "id": 70,
          "name": "Internet",
          "description": "M\u1ea1ng gia \u0111\u00ecnh",
          "icon": "icon_internet",
          "type": {
            "data": {
              "id": 6,
              "name": "Ti\u1ec7n \u00edch ",
              "description": ""
            }
          }
        },
        {
          "id": 71,
          "name": "C\u1eeda s\u1ed5",
          "description": "C\u1eeda s\u1ed5",
          "icon": "icon_windows",
          "type": {
            "data": {
              "id": 5,
              "name": "Ti\u1ec7n \u00edch ph\u00f2ng",
              "description": ""
            }
          }
        }
      ]
    },
    "amenityTypes": {
      "data": [
        {
          "id": 6,
          "name": "Ti\u1ec7n \u00edch ",
          "description": "",
          "amenities": {
            "data": [
              {
                "id": 17,
                "name": "Wifi",
                "description": "",
                "icon": "lst-icon-hotel-wifi"
              },
              {
                "id": 27,
                "name": "TV",
                "description": "",
                "icon": "lst-icon-tv"
              },
              {
                "id": 38,
                "name": "M\u00e1y gi\u1eb7t",
                "description": "",
                "icon": "lst-icon-washer"
              },
              {
                "id": 42,
                "name": "D\u1ea7u g\u1ed9i, d\u1ea7u x\u1ea3",
                "description": "",
                "icon": "lst-icon-shampoo"
              },
              {
                "id": 44,
                "name": "Gi\u1ea5y v\u1ec7 sinh",
                "description": "",
                "icon": "lst-icon-toilet-paper-1"
              },
              {
                "id": 53,
                "name": "Kh\u0103n t\u1eafm",
                "description": "",
                "icon": "lst-icon-towels"
              },
              {
                "id": 55,
                "name": "Kem \u0111\u00e1nh r\u0103ng",
                "description": "",
                "icon": "lst-icon-uniF12D"
              },
              {
                "id": 59,
                "name": "X\u00e0 ph\u00f2ng t\u1eafm",
                "description": "",
                "icon": "lst-icon-uniF126"
              },
              {
                "id": 69,
                "name": "M\u00e1y s\u1ea5y",
                "description": "",
                "icon": "lst-icon-hair-dryer"
              },
              {
                "id": 70,
                "name": "Internet",
                "description": "M\u1ea1ng gia \u0111\u00ecnh",
                "icon": "icon_internet"
              }
            ]
          }
        },
        {
          "id": 2,
          "name": "Ti\u1ec7n \u00edch b\u1ebfp",
          "description": "",
          "amenities": {
            "data": [
              {
                "id": 6,
                "name": "B\u1ebfp \u0111i\u1ec7n",
                "description": "",
                "icon": "lst-icon-stove-electric"
              },
              {
                "id": 7,
                "name": "L\u00f2 vi s\u00f3ng",
                "description": "",
                "icon": "lst-icon-microwave"
              },
              {
                "id": 8,
                "name": "T\u1ee7 l\u1ea1nh",
                "description": "",
                "icon": "lst-icon-refrigerator"
              }
            ]
          }
        },
        {
          "id": 3,
          "name": "Ti\u1ec7n \u00edch gi\u1ea3i tr\u00ed",
          "description": "",
          "amenities": {
            "data": [
              {
                "id": 5,
                "name": "BBQ",
                "description": "",
                "icon": "lst-icon-bbq-facilities"
              }
            ]
          }
        },
        {
          "id": 5,
          "name": "Ti\u1ec7n \u00edch ph\u00f2ng",
          "description": "",
          "amenities": {
            "data": [
              {
                "id": 22,
                "name": "Ban C\u00f4ng",
                "description": "",
                "icon": "lst-icon-balcony-terrace"
              },
              {
                "id": 71,
                "name": "C\u1eeda s\u1ed5",
                "description": "C\u1eeda s\u1ed5",
                "icon": "icon_windows"
              }
            ]
          }
        },
        {
          "id": 7,
          "name": "Ti\u1ec7n \u00edch n\u1ed5i b\u1eadt",
          "description": "Ti\u1ec7n \u00edch n\u1ed5i b\u1eadt",
          "amenities": {
            "data": [
              {
                "id": 66,
                "name": "Smart tivi",
                "description": "",
                "icon": "lst-icon-smart-tv"
              }
            ]
          }
        },
        {
          "id": 1,
          "name": "Ti\u1ec7n \u00edch gia \u0111\u00ecnh",
          "description": "",
          "amenities": {
            "data": [
              {
                "id": 36,
                "name": "Ph\u00f9 h\u1ee3p v\u1edbi tr\u1ebb nh\u1ecf",
                "description": "",
                "icon": "lst-icon-family-room"
              },
              {
                "id": 39,
                "name": "\u0110\u1ec7m b\u1ed5 sung",
                "description": "",
                "icon": "lst-icon-room-promotion"
              }
            ]
          }
        }
      ]
    },
    "destinations": {
      "data": [
        {
          "id": 1,
          "name": "Vietnam",
          "url": "vietnam"
        },
        {
          "id": 2716,
          "name": "Lam Dong",
          "url": "vietnam\/lam-dong"
        },
        {
          "id": 2767,
          "name": "Da Lat",
          "url": "vietnam\/lam-dong\/da-lat"
        },
        {
          "id": 2773,
          "name": "Phuong 3",
          "url": "vietnam\/lam-dong\/da-lat\/phuong-3"
        }
      ]
    },
    "coupon": {
      "data": []
    }
  },
  "code": 200,
  "request_id": "fd113f253c22e30ed5dfc86d32a30210"
}